source_fauna/__init__.py
source_fauna/run.py
source_fauna/serialize.py
source_fauna/source.py
source_fauna/spec.yaml
airbyte_source_fauna-0.1.9.dist-info/METADATA
airbyte_source_fauna-0.1.9.dist-info/WHEEL
airbyte_source_fauna-0.1.9.dist-info/entry_points.txt
airbyte_source_fauna-0.1.9.dist-info/RECORD
