Metadata-Version: 2.3
Name: airbyte-source-fauna
Version: 0.1.9
Summary: Source implementation for fauna.
License: MIT
Author: Airbyte
Author-email: contact@airbyte.io
Requires-Python: >=3.9,<3.12
Classifier: License :: OSI Approved :: MIT License
Classifier: Programming Language :: Python :: 3
Classifier: Programming Language :: Python :: 3.9
Classifier: Programming Language :: Python :: 3.10
Classifier: Programming Language :: Python :: 3.11
Requires-Dist: airbyte-cdk (<1.0)
Requires-Dist: faunadb (>=4.5.2,<5.0.0)
Project-URL: Documentation, https://docs.airbyte.com/integrations/sources/fauna
Project-URL: Homepage, https://airbyte.com
Project-URL: Repository, https://github.com/airbytehq/airbyte
